pixi_kernel/__init__.py
pixi_kernel/__main__.py
pixi_kernel/async_subprocess.py
pixi_kernel/compatibility.py
pixi_kernel/env.py
pixi_kernel/fallback.py
pixi_kernel/handlers.py
pixi_kernel/provisioner.py
pixi_kernel/readiness.py
pixi_kernel/types.py
pixi_kernel-0.6.7.data/data/etc/jupyter/jupyter_server_config.d/pixi_kernel.json
pixi_kernel-0.6.7.data/data/share/jupyter/kernels/pixi-kernel-ir/kernel.js
pixi_kernel-0.6.7.data/data/share/jupyter/kernels/pixi-kernel-ir/kernel.json
pixi_kernel-0.6.7.data/data/share/jupyter/kernels/pixi-kernel-ir/logo-64x64.png
pixi_kernel-0.6.7.data/data/share/jupyter/kernels/pixi-kernel-ir/logo-svg.svg
pixi_kernel-0.6.7.data/data/share/jupyter/kernels/pixi-kernel-python3/kernel.json
pixi_kernel-0.6.7.data/data/share/jupyter/kernels/pixi-kernel-python3/logo-32x32.png
pixi_kernel-0.6.7.data/data/share/jupyter/kernels/pixi-kernel-python3/logo-64x64.png
pixi_kernel-0.6.7.data/data/share/jupyter/kernels/pixi-kernel-python3/logo-svg.svg
pixi_kernel-0.6.7.data/data/share/jupyter/labextensions/pixi-kernel/package.json
pixi_kernel-0.6.7.data/data/share/jupyter/labextensions/pixi-kernel/schemas/pixi-kernel/package.json.orig
pixi_kernel-0.6.7.data/data/share/jupyter/labextensions/pixi-kernel/schemas/pixi-kernel/plugin.json
pixi_kernel-0.6.7.data/data/share/jupyter/labextensions/pixi-kernel/static/935.a8917cde6683e97f4741.js
pixi_kernel-0.6.7.data/data/share/jupyter/labextensions/pixi-kernel/static/remoteEntry.e6ad5b91eb3cf0d4562e.js
pixi_kernel-0.6.7.data/data/share/jupyter/labextensions/pixi-kernel/static/style.js
pixi_kernel-0.6.7.data/data/share/jupyter/labextensions/pixi-kernel/static/third-party-licenses.json
pixi_kernel-0.6.7.dist-info/METADATA
pixi_kernel-0.6.7.dist-info/WHEEL
pixi_kernel-0.6.7.dist-info/entry_points.txt
pixi_kernel-0.6.7.dist-info/licenses/LICENSE
pixi_kernel-0.6.7.dist-info/RECORD
