Metadata-Version: 2.4
Name: pixi-kernel
Version: 0.6.7
Summary: Jupyter kernels using Pixi for reproducible notebooks
Project-URL: Documentation, https://github.com/renan-r-santos/pixi-kernel
Project-URL: Homepage, https://github.com/renan-r-santos/pixi-kernel
Project-URL: Repository, https://github.com/renan-r-santos/pixi-kernel
Author-email: Renan Rodrigues dos Santos <renan.engmec@gmail.com>
License: MIT
License-File: LICENSE
Keywords: jupyter,jupyterlab,jupyterlab-extension,kernel,pixi
Classifier: Development Status :: 5 - Production/Stable
Classifier: Framework :: Jupyter
Classifier: Framework :: Jupyter :: JupyterLab
Classifier: Framework :: Jupyter :: JupyterLab :: 4
Classifier: Framework :: Jupyter :: JupyterLab :: Extensions
Classifier: Framework :: Jupyter :: JupyterLab :: Extensions :: Prebuilt
Classifier: Intended Audience :: Developers
Classifier: License :: OSI Approved :: MIT License
Classifier: Operating System :: OS Independent
Classifier: Programming Language :: Python
Classifier: Programming Language :: Python :: 3
Classifier: Programming Language :: Python :: 3 :: Only
Classifier: Programming Language :: Python :: 3.9
Classifier: Programming Language :: Python :: 3.10
Classifier: Programming Language :: Python :: 3.11
Classifier: Programming Language :: Python :: 3.12
Classifier: Programming Language :: Python :: 3.13
Classifier: Typing :: Typed
Requires-Python: <4.0,>=3.9
Requires-Dist: ipykernel>=6
Requires-Dist: jupyter-client>=7
Requires-Dist: jupyter-server>=2.4
Requires-Dist: msgspec>=0.18
Requires-Dist: returns>=0.23
Requires-Dist: tomli>=2; python_version < '3.11'
